{
  "projects": [
    {
      "name": "Happy Thoughts App",
      "image": "https://images.unsplash.com/photo-1557008075-7f2c5efa4cfd?ixlib=rb-4.0.3&ixid=M3wxMjA3fDB8MHxwaG90by1wYWdlfHx8fGVufDB8fHx8fA%3D%3D&auto=format&fit=crop&w=2497&q=80",
      "tags": [
        "HTML5",
        "CSS3",
        "JavaScript",
        "React",
        "APIs",
        "State"
      ],
      "netlify": "https://xingshappythoughts.netlify.app/",
      "github": "https://github.com/xingyin2024/project-happy-thoughts-vite"
    },
    {
      "name": "Survey App",
      "image": "https://images.unsplash.com/photo-1520792532857-293bd046307a?ixlib=rb-4.0.3&ixid=M3wxMjA3fDB8MHxwaG90by1wYWdlfHx8fGVufDB8fHx8fA%3D%3D&auto=format&fit=crop&w=2370&q=80",
      "tags": [
        "HTML5",
        "CSS3",
        "JavaScript",
        "React",
        "State"
      ],
      "netlify": "https://survey-personality.netlify.app/",
      "github": "https://github.com/xingyin2024/project-survey-vite"
    },
    {
      "name": "Album and Single Releases",
      "image": "https://images.unsplash.com/photo-1557008075-7f2c5efa4cfd?ixlib=rb-4.0.3&ixid=M3wxMjA3fDB8MHxwaG90by1wYWdlfHx8fGVufDB8fHx8fA%3D%3D&auto=format&fit=crop&w=2497&q=80",
      "tags": [
        "HTML5",
        "CSS3",
        "JavaScript",
        "React",
        "APIs"        
      ],
      "netlify": "https://xingsmusiclibary.netlify.app/",
      "github": "https://github.com/xingyin2024/project-music-releases-vite"
    },
    {
      "name": "Weather app",
      "image": "https://images.unsplash.com/photo-1520792532857-293bd046307a?ixlib=rb-4.0.3&ixid=M3wxMjA3fDB8MHxwaG90by1wYWdlfHx8fGVufDB8fHx8fA%3D%3D&auto=format&fit=crop&w=2370&q=80",
      "tags": [
        "HTML5",
        "CSS3",
        "JavaScript",
        "React",
        "APIs"
      ],
      "netlify": "https://xingsweatherapp.netlify.app/",
      "github": "https://github.com/xingyin2024/project-weather-app"
    },
    {
      "name": "Book Library",
      "image": "https://images.unsplash.com/photo-1557008075-7f2c5efa4cfd?ixlib=rb-4.0.3&ixid=M3wxMjA3fDB8MHxwaG90by1wYWdlfHx8fGVufDB8fHx8fA%3D%3D&auto=format&fit=crop&w=2497&q=80",
      "tags": [
        "HTML5",
        "CSS3",
        "JavaScript",
        "Mob-programmning"
      ],
      "netlify": "https://xingsbooklibrary.netlify.app/",
      "github": "https://github.com/xingyin2024/project-library"
    },
    {
      "name": "Travel Chatbot",
      "image": "https://images.unsplash.com/photo-1520792532857-293bd046307a?ixlib=rb-4.0.3&ixid=M3wxMjA3fDB8MHxwaG90by1wYWdlfHx8fGVufDB8fHx8fA%3D%3D&auto=format&fit=crop&w=2370&q=80",
      "tags": [
        "HTML5",
        "CSS3",
        "JavaScript",
        "Mob-programmning"
      ],
      "netlify": "https://travelchatbot.netlify.app/",
      "github": "https://github.com/xingyin2024/project-chatbot"
    },
    {
      "name": "JavaScript Pizzeria",
      "image": "https://images.unsplash.com/photo-1520792532857-293bd046307a?ixlib=rb-4.0.3&ixid=M3wxMjA3fDB8MHxwaG90by1wYWdlfHx8fGVufDB8fHx8fA%3D%3D&auto=format&fit=crop&w=2370&q=80",
      "tags": [
        "HTML5",
        "CSS3",
        "JavaScript",
        "React",
        "APIs"
      ],
      "netlify": "https://xingspizzeria.netlify.app/",
      "github": "https://github.com/xingyin2024/project-pizza"
    },
    {
      "name": "Business Site ",
      "image": "https://images.unsplash.com/photo-1557008075-7f2c5efa4cfd?ixlib=rb-4.0.3&ixid=M3wxMjA3fDB8MHxwaG90by1wYWdlfHx8fGVufDB8fHx8fA%3D%3D&auto=format&fit=crop&w=2497&q=80",
      "tags": [
        "HTML5",
        "CSS3",
        "JavaScript",
        "Mob-programmning"
      ],
      "netlify": "https://xingspress.netlify.app/",
      "github": "https://github.com/xingyin2024/project-business-site"
    },
    {
      "name": "News Site",
      "image": "https://images.unsplash.com/photo-1520792532857-293bd046307a?ixlib=rb-4.0.3&ixid=M3wxMjA3fDB8MHxwaG90by1wYWdlfHx8fGVufDB8fHx8fA%3D%3D&auto=format&fit=crop&w=2370&q=80",
      "tags": [
        "HTML5",
        "CSS3",
        "JavaScript",
        "Mob-programmning"
      ],
      "netlify": "https://xingsnews.netlify.app/",
      "github": "https://github.com/xingyin2024/project-news-site"
    }
  ]
}