[
  {
    "projectName": "project-business-site",
    "imageUrl": "businesssite.png"
  },
  {
    "projectName": "project-survey-vite",
    "imageUrl": "bedtimestories.png"
  },
  {
    "projectName": "project-happy-thoughts-vite",
    "imageUrl": "happythought.png"
  },
  {
    "projectName": "project-music-releases-vite",
    "imageUrl": "music.png"
  },
  {
    "projectName": "project-weather-app",
    "imageUrl": "weatherapp.png"
  },
  {
    "projectName": "project-library",
    "imageUrl": "library.png"
  },
  {
    "projectName": "project-chatbot",
    "imageUrl": "oceanbot.png"
  },
  {
    "projectName": "project-pizza",
    "imageUrl": "pizzeria.png"
  },
  {
    "projectName": "project-news-site",
    "imageUrl": "oceannews.png"
  },
  {
    "projectName": "project-p1-first-webpage",
    "imageUrl": "mypage.png"
  }
]
