{
  "projects": [
    {
      "id": 1,
      "repoName": "project-happy-thoughts-vite",
      "displayName": "Happy Thoughts",
      "imageUrl": "images/happy-thoughts.png",
      "description": "A project focused on...",
      "tags": [
        "HTML5",
        "CSS3",
        "JavaScript"
      ],
      "netlifyUrl": "https://maria-happy-thoughts.netlify.app"
    },
    {
      "id": 2,
      "repoName": "project-survey-vite",
      "displayName": "Survey ADHD",
      "imageUrl": "images/survey.png",
      "description": "A project focused on...",
      "tags": [
        "HTML5",
        "CSS3",
        "JavaScript"
      ],
      "netlifyUrl": "https://surveyformbyam.netlify.app"
    },
    {
      "id": 3,
      "repoName": "project-music-releases-vite",
      "displayName": "Music Release",
      "imageUrl": "images/spotify.png",
      "description": "A project focused on...",
      "tags": [
        "HTML5",
        "CSS3",
        "JavaScript"
      ],
      "netlifyUrl": "https://musiclibrary-bmm.netlify.app"
    },
    {
      "id": 4,
      "repoName": "project-weather-app",
      "displayName": "Weather App",
      "imageUrl": "images/weatherApp.png",
      "description": "A project focused on...",
      "tags": [
        "HTML5",
        "CSS3",
        "JavaScript"
      ],
      "netlifyUrl": "https://weatherapp-bmm.netlify.app"
    },
    {
      "id": 5,
      "repoName": "project-library",
      "displayName": "Flavour Fuse",
      "imageUrl": "images/project-library.png",
      "description": "A project focused on...",
      "tags": [
        "HTML5",
        "CSS3",
        "JavaScript"
      ],
      "netlifyUrl": "https://flavourfus.netlify.app"
    },
    {
      "id": 6,
      "repoName": "project-chatbot",
      "displayName": "Chatbot built in javascript",
      "imageUrl": "images/chatbot.png",
      "description": "A project focused on...",
      "tags": [
        "HTML5",
        "CSS3",
        "React"
      ],
      "netlifyUrl": "https://genieplant.netlify.app"
    },
    {
      "id": 7,
      "repoName": "project-news-site",
      "displayName": "My first website",
      "imageUrl": "images/news-site.png",
      "description": "A project focused on...",
      "tags": [
        "HTML5",
        "CSS3"
      ],
      "netlifyUrl": "https://ecobloomnews.netlify.app"
    }
  ]
}
   