{
  "Articles": [
    {
      "name": "Reflections on Attending a Web Developer Bootcamp: Halfway Through",
      "image": "./Article.png",
      "tags": [
        "October 21"
      ],
      "description": "In August, I began my journey into web development through a boot camp. This experience has not only taught me valuable skills but also contributed to my personal development. Here are my reflections on the challenges and lessons I've encountered so far.",
      "Link": "https://www.linkedin.com/pulse/reflections-attending-web-developer-bootcamp-halfway-through-hansen-vryxf/?trackingId=fmSgPhJGT%2FmKep9F0FmgKw%3D%3D"
    }
  ]
}